multiformats_config/__init__.py
multiformats_config/config.py
multiformats_config/multibase-table.json
multiformats_config/multibase.py
multiformats_config/multicodec-table.json
multiformats_config/multicodec.py
multiformats_config/py.typed
multiformats_config-0.3.1.dist-info/LICENSE
multiformats_config-0.3.1.dist-info/METADATA
multiformats_config-0.3.1.dist-info/WHEEL
multiformats_config-0.3.1.dist-info/top_level.txt
multiformats_config-0.3.1.dist-info/RECORD
